qaoalib/__init__.py
qaoalib/json.py
qaoalib/math.py
qaoalib/utils.py
qaoalib/version.py
qaoalib/models/__init__.py
qaoalib/models/result.py
qaoalib/solver/__init__.py
qaoalib/solver/vqe.py
qaoalib-0.2.1.dist-info/LICENSE
qaoalib-0.2.1.dist-info/METADATA
qaoalib-0.2.1.dist-info/WHEEL
qaoalib-0.2.1.dist-info/top_level.txt
qaoalib-0.2.1.dist-info/RECORD
