Metadata-Version: 2.1
Name: qaoalib
Version: 0.2.1
Summary: A package for QAOA Maxcut calculations
Home-page: https://github.com/xenoicwyce/qaoalib
Author: Xinwei Lee
Author-email: xenoicwyce@gmail.com
Classifier: Programming Language :: Python :: 3
Classifier: License :: OSI Approved :: MIT License
Classifier: Operating System :: OS Independent
Requires-Python: >=3.9
License-File: LICENSE
Requires-Dist: qiskit
Requires-Dist: qiskit-optimization
Requires-Dist: qiskit-aer
Requires-Dist: numpy ==1.26.0
Requires-Dist: scipy
Requires-Dist: pytest
Requires-Dist: pytest-cov
Requires-Dist: matplotlib
Requires-Dist: networkx
Requires-Dist: pydantic
